ccd2rdmol/__init__.py
ccd2rdmol/cli.py
ccd2rdmol/converter.py
ccd2rdmol/models.py
ccd2rdmol/sanitizer.py
ccd2rdmol-0.2.1.dist-info/METADATA
ccd2rdmol-0.2.1.dist-info/WHEEL
ccd2rdmol-0.2.1.dist-info/entry_points.txt
ccd2rdmol-0.2.1.dist-info/licenses/LICENSE
ccd2rdmol-0.2.1.dist-info/RECORD
