Metadata-Version: 2.4
Name: ccd2rdmol
Version: 0.2.1
Summary: Convert PDB Chemical Component Dictionary (CCD) files to RDKit molecules
Project-URL: Repository, https://github.com/N283T/ccd2rdmol
Author: N283T
License: MIT
License-File: LICENSE
Keywords: ccd,chemistry,molecular,pdb,rdkit
Classifier: Development Status :: 4 - Beta
Classifier: Intended Audience :: Science/Research
Classifier: License :: OSI Approved :: MIT License
Classifier: Programming Language :: Python :: 3.10
Classifier: Programming Language :: Python :: 3.11
Classifier: Programming Language :: Python :: 3.12
Classifier: Programming Language :: Python :: 3.13
Classifier: Programming Language :: Python :: 3.14
Classifier: Topic :: Scientific/Engineering :: Chemistry
Requires-Python: >=3.10
Requires-Dist: gemmi>=0.7.0
Requires-Dist: rdkit>=2024.3.1
Provides-Extra: cli
Requires-Dist: rich>=14.0.0; extra == 'cli'
Requires-Dist: typer>=0.21.0; extra == 'cli'
